distillseq/__init__.py
distillseq/datasets/__init__.py
distillseq/datasets/teacher.py
distillseq/datasets/wrapper.py
distillseq/methods/__init__.py
distillseq/methods/base.py
distillseq/methods/glm_diversity.py
distillseq/methods/gradient_matching.py
distillseq/methods/kmer_diversity.py
distillseq/methods/model_confidence_diversity.py
distillseq/methods/random_sampling.py
distillseq/utils/__init__.py
distillseq/utils/divergence.py
distillseq/utils/kmer.py
distillseq/utils/sequence.py
distillseq/utils/uncertainty.py
distillseq-0.1.0.dist-info/licenses/LICENSE
distillseq-0.1.0.dist-info/METADATA
distillseq-0.1.0.dist-info/WHEEL
distillseq-0.1.0.dist-info/top_level.txt
distillseq-0.1.0.dist-info/RECORD
