Metadata-Version: 2.4
Name: distillseq
Version: 0.1.0
Summary: Data distillation methods for genomic sequence-to-function models
Author-email: Your Name <your.email@example.com>
License: MIT
Project-URL: Homepage, https://github.com/yourusername/distillseq
Project-URL: Documentation, https://distillseq.readthedocs.io
Project-URL: Repository, https://github.com/yourusername/distillseq
Project-URL: Bug Tracker, https://github.com/yourusername/distillseq/issues
Keywords: genomics,deep-learning,data-distillation,dataset-condensation,bioinformatics
Classifier: Development Status :: 3 - Alpha
Classifier: Intended Audience :: Science/Research
Classifier: License :: OSI Approved :: MIT License
Classifier: Programming Language :: Python :: 3
Classifier: Programming Language :: Python :: 3.8
Classifier: Programming Language :: Python :: 3.9
Classifier: Programming Language :: Python :: 3.10
Classifier: Programming Language :: Python :: 3.11
Classifier: Topic :: Scientific/Engineering :: Bio-Informatics
Classifier: Topic :: Scientific/Engineering :: Artificial Intelligence
Requires-Python: >=3.8
License-File: LICENSE
Requires-Dist: torch>=2.0.0
Requires-Dist: numpy>=1.20.0
Requires-Dist: scipy>=1.7.0
Requires-Dist: tqdm>=4.60.0
Requires-Dist: scikit-learn>=1.0.0
Provides-Extra: dev
Requires-Dist: pytest>=7.0.0; extra == "dev"
Requires-Dist: pytest-cov>=3.0.0; extra == "dev"
Requires-Dist: black>=22.0.0; extra == "dev"
Requires-Dist: flake8>=4.0.0; extra == "dev"
Requires-Dist: mypy>=0.950; extra == "dev"
Provides-Extra: glm
Requires-Dist: transformers>=4.20.0; extra == "glm"
Provides-Extra: wandb
Requires-Dist: wandb>=0.12.0; extra == "wandb"
Provides-Extra: all
Requires-Dist: transformers>=4.20.0; extra == "all"
Requires-Dist: wandb>=0.12.0; extra == "all"
Dynamic: license-file
